rdata/__init__.py
rdata/_read.py
rdata/py.typed
rdata/testing.py
rdata/conversion/__init__.py
rdata/conversion/_conversion.py
rdata/parser/__init__.py
rdata/parser/_ascii.py
rdata/parser/_parser.py
rdata/parser/_xdr.py
rdata/tests/__init__.py
rdata/tests/test_rdata.py
rdata/tests/data/test_altrep_compact_intseq.rda
rdata/tests/data/test_altrep_compact_intseq_asymmetric.rda
rdata/tests/data/test_altrep_compact_realseq.rda
rdata/tests/data/test_altrep_compact_realseq_asymmetric.rda
rdata/tests/data/test_altrep_deferred_string.rda
rdata/tests/data/test_altrep_wrap_logical.rda
rdata/tests/data/test_altrep_wrap_real.rda
rdata/tests/data/test_altrep_wrap_string.rda
rdata/tests/data/test_ascii_v2.rda
rdata/tests/data/test_ascii_v2.rds
rdata/tests/data/test_ascii_v3.rda
rdata/tests/data/test_ascii_v3.rds
rdata/tests/data/test_ascii_win_v2.rda
rdata/tests/data/test_ascii_win_v2.rds
rdata/tests/data/test_ascii_win_v3.rda
rdata/tests/data/test_ascii_win_v3.rds
rdata/tests/data/test_builtin.rda
rdata/tests/data/test_complex.rda
rdata/tests/data/test_dataframe.rda
rdata/tests/data/test_dataframe.rds
rdata/tests/data/test_dataframe_rownames.rda
rdata/tests/data/test_dataframe_v3.rda
rdata/tests/data/test_dataframe_v3.rds
rdata/tests/data/test_empty_function.rda
rdata/tests/data/test_empty_function_uncompiled.rda
rdata/tests/data/test_empty_str.rda
rdata/tests/data/test_emptyenv.rda
rdata/tests/data/test_encodings.rda
rdata/tests/data/test_encodings_v3.rda
rdata/tests/data/test_environment.rda
rdata/tests/data/test_expression.rda
rdata/tests/data/test_file.rda
rdata/tests/data/test_full_named_matrix.rda
rdata/tests/data/test_full_named_matrix.rds
rdata/tests/data/test_function.rda
rdata/tests/data/test_function_arg.rda
rdata/tests/data/test_half_named_matrix.rda
rdata/tests/data/test_list.rda
rdata/tests/data/test_list_attrs.rda
rdata/tests/data/test_logical.rda
rdata/tests/data/test_matrix.rda
rdata/tests/data/test_minimal_function.rda
rdata-0.11.2.dist-info/LICENSE
rdata-0.11.2.dist-info/METADATA
rdata-0.11.2.dist-info/WHEEL
rdata-0.11.2.dist-info/top_level.txt
rdata-0.11.2.dist-info/RECORD
