Metadata-Version: 2.1
Name: rdata
Version: 0.11.2
Summary: Read R datasets from Python.
Author-email: Carlos Ramos Carreño <vnmabus@gmail.com>
Maintainer-email: Carlos Ramos Carreño <vnmabus@gmail.com>
License: MIT License
Project-URL: homepage, https://github.com/vnmabus/rdata
Project-URL: documentation, https://rdata.readthedocs.io
Project-URL: repository, https://github.com/vnmabus/rdata
Keywords: rdata,r,dataset
Classifier: Development Status :: 4 - Beta
Classifier: Intended Audience :: Developers
Classifier: Intended Audience :: Science/Research
Classifier: License :: OSI Approved :: MIT License
Classifier: Natural Language :: English
Classifier: Operating System :: OS Independent
Classifier: Programming Language :: Python :: 3
Classifier: Programming Language :: Python :: 3.9
Classifier: Programming Language :: Python :: 3.10
Classifier: Programming Language :: Python :: 3.11
Classifier: Programming Language :: Python :: 3.12
Classifier: Topic :: File Formats
Classifier: Topic :: Scientific/Engineering :: Mathematics
Classifier: Topic :: Software Development :: Libraries :: Python Modules
Classifier: Typing :: Typed
Requires-Python: >=3.9
License-File: LICENSE
Requires-Dist: numpy
Requires-Dist: xarray
Requires-Dist: pandas
Requires-Dist: typing_extensions>4.4
Provides-Extra: docs
Requires-Dist: igraph; extra == "docs"
Requires-Dist: ipywidgets; extra == "docs"
Requires-Dist: jupyterlite-sphinx; extra == "docs"
Requires-Dist: jupyterlite-pyodide-kernel; extra == "docs"
Requires-Dist: matplotlib; extra == "docs"
Requires-Dist: myst-parser; extra == "docs"
Requires-Dist: pydata-sphinx-theme; extra == "docs"
Requires-Dist: sphinx>=3.1; extra == "docs"
Requires-Dist: sphinx-codeautolink; extra == "docs"
Requires-Dist: sphinx-gallery; extra == "docs"
Provides-Extra: typing
Requires-Dist: matplotlib>=3.8; extra == "typing"
Requires-Dist: mypy; extra == "typing"
Requires-Dist: pandas-stubs; extra == "typing"
Provides-Extra: test
Requires-Dist: pytest; extra == "test"
Requires-Dist: pytest-cov; extra == "test"
Requires-Dist: numpy>=1.14; extra == "test"
